nose_skinny_report/__init__.py
nose_skinny_report/report.py
nose_skinny_report-0.0.5.dist-info/LICENSE
nose_skinny_report-0.0.5.dist-info/METADATA
nose_skinny_report-0.0.5.dist-info/WHEEL
nose_skinny_report-0.0.5.dist-info/top_level.txt
nose_skinny_report-0.0.5.dist-info/RECORD
