Metadata-Version: 2.1
Name: nose-skinny-report
Version: 0.0.5
Summary: UNKNOWN
Home-page: UNKNOWN
Author: UNKNOWN
Author-email: UNKNOWN
License: UNKNOWN
Platform: UNKNOWN
Requires-Dist: nose2 (>=0.10.0)
